pyptrs/__init__.py
pyptrs/pyptrs.py
pyptrs-1.0.1.post2.dist-info/METADATA
pyptrs-1.0.1.post2.dist-info/WHEEL
pyptrs-1.0.1.post2.dist-info/RECORD
