Metadata-Version: 2.4
Name: pyptrs
Version: 1.0.1.post2
Summary: Real pointers and some memory utilities for python
Project-URL: Homepage, https://github.com/pyhacks/pyptrs
Author-email: pyhacks <enginyildirim111@gmail.com>
Keywords: memory,pointers,ptrs
